[{"abbr":"AL","corporate":{"prevRank":23,"prevValue":5.24,"rank":23,"value":5.22},"id":1,"individual":{"prevRank":30,"prevValue":4.82,"rank":30,"value":4.81},"name":"Alabama","neighbors":[28,47,13,12],"property":{"prevRank":15,"prevValue":5.51,"rank":19,"value":5.33},"sales":{"prevRank":50,"prevValue":2.61,"rank":50,"value":2.56},"total":{"prevRank":40,"prevValue":4.53,"rank":41,"value":4.47},"unemployment":{"prevRank":18,"prevValue":5.26,"rank":14,"value":5.36}},{"abbr":"AK","corporate":{"prevRank":26,"prevValue":5.12,"rank":26,"value":5.11},"id":2,"individual":{"prevRank":1,"prevValue":10.0,"rank":1,"value":10.0},"name":"Alaska","neighbors":[],"property":{"prevRank":25,"prevValue":5.07,"rank":22,"value":5.2},"sales":{"prevRank":5,"prevValue":8.08,"rank":5,"value":8.1},"total":{"prevRank":3,"prevValue":7.22,"rank":3,"value":7.28},"unemployment":{"prevRank":46,"prevValue":4.31,"rank":45,"value":4.4}},{"abbr":"AZ","corporate":{"prevRank":22,"prevValue":5.28,"rank":22,"value":5.27},"id":4,"individual":{"prevRank":17,"prevValue":5.51,"rank":17,"value":5.49},"name":"Arizona","neighbors":[6,32,49,8,35],"property":{"prevRank":8,"prevValue":6.32,"rank":11,"value":5.69},"sales":{"prevRank":40,"prevValue":4.02,"rank":40,"value":4.05},"total":{"prevRank":20,"prevValue":5.26,"rank":24,"value":5.13},"unemployment":{"prevRank":6,"prevValue":5.67,"rank":8,"value":5.6}},{"abbr":"AR","corporate":{"prevRank":34,"prevValue":4.8,"rank":34,"value":4.82},"id":5,"individual":{"prevRank":40,"prevValue":4.07,"rank":41,"value":4.18},"name":"Arkansas","neighbors":[29,47,28,22,48,40],"property":{"prevRank":29,"prevValue":5.0,"rank":25,"value":5.17},"sales":{"prevRank":46,"prevValue":3.58,"rank":46,"value":3.57},"total":{"prevRank":46,"prevValue":4.34,"rank":45,"value":4.39},"unemployment":{"prevRank":23,"prevValue":4.98,"rank":23,"value":5.01}},{"abbr":"CA","corporate":{"prevRank":28,"prevValue":4.94,"rank":28,"value":4.92},"id":6,"individual":{"prevRank":49,"prevValue":2.54,"rank":49,"value":2.53},"name":"California","neighbors":[41,32,4],"property":{"prevRank":16,"prevValue":5.44,"rank":14,"value":5.48},"sales":{"prevRank":45,"prevValue":3.74,"rank":45,"value":3.75},"total":{"prevRank":48,"prevValue":4.02,"rank":49,"value":4.0},"unemployment":{"prevRank":22,"prevValue":5.05,"rank":21,"value":5.09}},{"abbr":"CO","corporate":{"prevRank":7,"prevValue":5.82,"rank":10,"value":5.8},"id":8,"individual":{"prevRank":14,"prevValue":5.85,"rank":14,"value":5.84},"name":"Colorado","neighbors":[56,31,20,40,35,4,49],"property":{"prevRank":14,"prevValue":5.52,"rank":32,"value":4.73},"sales":{"prevRank":37,"prevValue":4.34,"rank":36,"value":4.37},"total":{"prevRank":17,"prevValue":5.3,"rank":21,"value":5.18},"unemployment":{"prevRank":43,"prevValue":4.53,"rank":41,"value":4.52}},{"abbr":"CT","corporate":{"prevRank":27,"prevValue":5.11,"rank":27,"value":5.1},"id":9,"individual":{"prevRank":43,"prevValue":3.88,"rank":44,"value":3.87},"name":"Connecticut","neighbors":[36,25,44],"property":{"prevRank":50,"prevValue":2.56,"rank":50,"value":2.34},"sales":{"prevRank":26,"prevValue":4.75,"rank":26,"value":4.78},"total":{"prevRank":47,"prevValue":4.23,"rank":47,"value":4.24},"unemployment":{"prevRank":21,"prevValue":5.07,"rank":22,"value":5.07}},{"abbr":"DE","corporate":{"prevRank":50,"prevValue":2.91,"rank":50,"value":2.45},"id":10,"individual":{"prevRank":41,"prevValue":4.06,"rank":42,"value":4.05},"name":"Delaware","neighbors":[24,42,34],"property":{"prevRank":6,"prevValue":6.34,"rank":4,"value":6.3},"sales":{"prevRank":2,"prevValue":9.02,"rank":2,"value":9.04},"total":{"prevRank":11,"prevValue":5.57,"rank":13,"value":5.44},"unemployment":{"prevRank":3,"prevValue":5.86,"rank":3,"value":5.86}},{"abbr":"FL","corporate":{"prevRank":9,"prevValue":5.63,"rank":6,"value":5.94},"id":12,"individual":{"prevRank":1,"prevValue":10.0,"rank":1,"value":10.0},"name":"Florida","neighbors":[1,13],"property":{"prevRank":13,"prevValue":5.61,"rank":13,"value":5.59},"sales":{"prevRank":23,"prevValue":4.86,"rank":21,"value":4.96},"total":{"prevRank":4,"prevValue":6.8,"rank":4,"value":6.89},"unemployment":{"prevRank":2,"prevValue":6.01,"rank":2,"value":6.0}},{"abbr":"GA","corporate":{"prevRank":6,"prevValue":5.89,"rank":7,"value":5.93},"id":13,"individual":{"prevRank":36,"prevValue":4.53,"rank":36,"value":4.56},"name":"Georgia","neighbors":[12,1,47,37,45],"property":{"prevRank":28,"prevValue":5.01,"rank":24,"value":5.18},"sales":{"prevRank":29,"prevValue":4.61,"rank":27,"value":4.68},"total":{"prevRank":32,"prevValue":4.91,"rank":31,"value":4.97},"unemployment":{"prevRank":39,"prevValue":4.61,"rank":39,"value":4.64}},{"abbr":"HI","corporate":{"prevRank":16,"prevValue":5.46,"rank":18,"value":5.45},"id":15,"individual":{"prevRank":47,"prevValue":3.52,"rank":47,"value":3.51},"name":"Hawaii","neighbors":[],"property":{"prevRank":11,"prevValue":5.87,"rank":9,"value":5.8},"sales":{"prevRank":30,"prevValue":4.6,"rank":30,"value":4.61},"total":{"prevRank":37,"prevValue":4.68,"rank":38,"value":4.66},"unemployment":{"prevRank":28,"prevValue":4.86,"rank":25,"value":4.96}},{"abbr":"ID","corporate":{"prevRank":29,"prevValue":4.93,"rank":29,"value":4.92},"id":16,"individual":{"prevRank":26,"prevValue":5.03,"rank":26,"value":5.01},"name":"Idaho","neighbors":[30,56,49,32,41,53],"property":{"prevRank":4,"prevValue":6.49,"rank":3,"value":6.44},"sales":{"prevRank":12,"prevValue":5.33,"rank":9,"value":5.38},"total":{"prevRank":21,"prevValue":5.23,"rank":20,"value":5.2},"unemployment":{"prevRank":48,"prevValue":4.01,"rank":48,"value":4.01}},{"abbr":"IL","corporate":{"prevRank":36,"prevValue":4.65,"rank":36,"value":4.63},"id":17,"individual":{"prevRank":13,"prevValue":5.87,"rank":13,"value":5.85},"name":"Illinois","neighbors":[18,21,29,19,55],"property":{"prevRank":40,"prevValue":4.1,"rank":48,"value":3.63},"sales":{"prevRank":33,"prevValue":4.47,"rank":38,"value":4.26},"total":{"prevRank":35,"prevValue":4.87,"rank":36,"value":4.75},"unemployment":{"prevRank":40,"prevValue":4.58,"rank":43,"value":4.49}},{"abbr":"IN","corporate":{"prevRank":11,"prevValue":5.61,"rank":12,"value":5.64},"id":18,"individual":{"prevRank":15,"prevValue":5.74,"rank":15,"value":5.77},"name":"Indiana","neighbors":[26,39,21,17],"property":{"prevRank":2,"prevValue":6.52,"rank":2,"value":6.47},"sales":{"prevRank":20,"prevValue":5.0,"rank":20,"value":5.0},"total":{"prevRank":10,"prevValue":5.59,"rank":9,"value":5.58},"unemployment":{"prevRank":25,"prevValue":4.96,"rank":27,"value":4.96}},{"abbr":"IA","corporate":{"prevRank":48,"prevValue":3.58,"rank":46,"value":4.03},"id":19,"individual":{"prevRank":42,"prevValue":4.03,"rank":40,"value":4.29},"name":"Iowa","neighbors":[27,55,17,29,31,46],"property":{"prevRank":35,"prevValue":4.62,"rank":38,"value":4.38},"sales":{"prevRank":15,"prevValue":5.18,"rank":14,"value":5.16},"total":{"prevRank":42,"prevValue":4.38,"rank":40,"value":4.5},"unemployment":{"prevRank":35,"prevValue":4.72,"rank":37,"value":4.72}},{"abbr":"KS","corporate":{"prevRank":35,"prevValue":4.66,"rank":31,"value":4.87},"id":20,"individual":{"prevRank":23,"prevValue":5.09,"rank":24,"value":5.07},"name":"Kansas","neighbors":[31,29,40,8],"property":{"prevRank":20,"prevValue":5.32,"rank":30,"value":5.02},"sales":{"prevRank":38,"prevValue":4.3,"rank":37,"value":4.34},"total":{"prevRank":34,"prevValue":4.88,"rank":35,"value":4.88},"unemployment":{"prevRank":14,"prevValue":5.41,"rank":13,"value":5.41}},{"abbr":"KY","corporate":{"prevRank":17,"prevValue":5.46,"rank":19,"value":5.45},"id":21,"individual":{"prevRank":18,"prevValue":5.47,"rank":18,"value":5.47},"name":"Kentucky","neighbors":[18,39,54,51,47,29,17],"property":{"prevRank":36,"prevValue":4.55,"rank":21,"value":5.2},"sales":{"prevRank":14,"prevValue":5.19,"rank":13,"value":5.21},"total":{"prevRank":24,"prevValue":5.1,"rank":19,"value":5.23},"unemployment":{"prevRank":49,"prevValue":3.91,"rank":49,"value":4.0}},{"abbr":"LA","corporate":{"prevRank":37,"prevValue":4.62,"rank":35,"value":4.76},"id":22,"individual":{"prevRank":32,"prevValue":4.73,"rank":32,"value":4.71},"name":"Louisiana","neighbors":[48,5,28],"property":{"prevRank":33,"prevValue":4.79,"rank":23,"value":5.18},"sales":{"prevRank":48,"prevValue":3.04,"rank":49,"value":2.94},"total":{"prevRank":41,"prevValue":4.41,"rank":42,"value":4.46},"unemployment":{"prevRank":4,"prevValue":5.79,"rank":4,"value":5.78}},{"abbr":"ME","corporate":{"prevRank":38,"prevValue":4.59,"rank":37,"value":4.58},"id":23,"individual":{"prevRank":22,"prevValue":5.14,"rank":22,"value":5.13},"name":"Maine","neighbors":[33],"property":{"prevRank":43,"prevValue":3.8,"rank":40,"value":4.34},"sales":{"prevRank":8,"prevValue":5.66,"rank":8,"value":5.63},"total":{"prevRank":33,"prevValue":4.9,"rank":29,"value":4.99},"unemployment":{"prevRank":32,"prevValue":4.8,"rank":33,"value":4.8}},{"abbr":"MD","corporate":{"prevRank":32,"prevValue":4.88,"rank":33,"value":4.87},"id":24,"individual":{"prevRank":45,"prevValue":3.67,"rank":45,"value":3.64},"name":"Maryland","neighbors":[51,54,42,11,10],"property":{"prevRank":42,"prevValue":3.85,"rank":43,"value":4.17},"sales":{"prevRank":19,"prevValue":5.02,"rank":18,"value":5.04},"total":{"prevRank":43,"prevValue":4.37,"rank":44,"value":4.42},"unemployment":{"prevRank":33,"prevValue":4.79,"rank":34,"value":4.79}},{"abbr":"MA","corporate":{"prevRank":39,"prevValue":4.58,"rank":38,"value":4.56},"id":25,"individual":{"prevRank":11,"prevValue":5.96,"rank":11,"value":5.94},"name":"Massachusetts","neighbors":[44,9,36,33,50],"property":{"prevRank":48,"prevValue":3.29,"rank":44,"value":3.84},"sales":{"prevRank":13,"prevValue":5.2,"rank":12,"value":5.23},"total":{"prevRank":36,"prevValue":4.81,"rank":34,"value":4.92},"unemployment":{"prevRank":50,"prevValue":3.29,"rank":50,"value":3.28}},{"abbr":"MI","corporate":{"prevRank":18,"prevValue":5.42,"rank":20,"value":5.41},"id":26,"individual":{"prevRank":12,"prevValue":5.95,"rank":12,"value":5.93},"name":"Michigan","neighbors":[55,18,39],"property":{"prevRank":24,"prevValue":5.09,"rank":35,"value":4.57},"sales":{"prevRank":9,"prevValue":5.53,"rank":10,"value":5.38},"total":{"prevRank":12,"prevValue":5.54,"rank":14,"value":5.42},"unemployment":{"prevRank":17,"prevValue":5.27,"rank":18,"value":5.18}},{"abbr":"MN","corporate":{"prevRank":44,"prevValue":4.33,"rank":45,"value":4.17},"id":27,"individual":{"prevRank":46,"prevValue":3.61,"rank":46,"value":3.59},"name":"Minnesota","neighbors":[55,19,46,38],"property":{"prevRank":26,"prevValue":5.07,"rank":31,"value":4.77},"sales":{"prevRank":28,"prevValue":4.63,"rank":28,"value":4.65},"total":{"prevRank":45,"prevValue":4.35,"rank":46,"value":4.26},"unemployment":{"prevRank":34,"prevValue":4.78,"rank":32,"value":4.82}},{"abbr":"MS","corporate":{"prevRank":10,"prevValue":5.63,"rank":13,"value":5.61},"id":28,"individual":{"prevRank":27,"prevValue":4.9,"rank":27,"value":4.89},"name":"Mississippi","neighbors":[22,5,47,1],"property":{"prevRank":37,"prevValue":4.52,"rank":37,"value":4.47},"sales":{"prevRank":34,"prevValue":4.46,"rank":32,"value":4.49},"total":{"prevRank":31,"prevValue":4.96,"rank":32,"value":4.96},"unemployment":{"prevRank":5,"prevValue":5.77,"rank":5,"value":5.73}},{"abbr":"MO","corporate":{"prevRank":5,"prevValue":5.96,"rank":3,"value":6.36},"id":29,"individual":{"prevRank":24,"prevValue":5.07,"rank":23,"value":5.1},"name":"Missouri","neighbors":[19,17,21,47,5,40,20,31],"property":{"prevRank":7,"prevValue":6.33,"rank":8,"value":5.84},"sales":{"prevRank":24,"prevValue":4.8,"rank":24,"value":4.81},"total":{"prevRank":14,"prevValue":5.43,"rank":12,"value":5.45},"unemployment":{"prevRank":9,"prevValue":5.56,"rank":7,"value":5.65}},{"abbr":"MT","corporate":{"prevRank":21,"prevValue":5.35,"rank":21,"value":5.33},"id":30,"individual":{"prevRank":25,"prevValue":5.03,"rank":25,"value":5.02},"name":"Montana","neighbors":[38,46,56,16],"property":{"prevRank":12,"prevValue":5.74,"rank":28,"value":5.15},"sales":{"prevRank":3,"prevValue":8.94,"rank":3,"value":8.96},"total":{"prevRank":5,"prevValue":6.16,"rank":5,"value":6.07},"unemployment":{"prevRank":20,"prevValue":5.1,"rank":20,"value":5.1}},{"abbr":"NE","corporate":{"prevRank":31,"prevValue":4.88,"rank":32,"value":4.87},"id":31,"individual":{"prevRank":21,"prevValue":5.16,"rank":21,"value":5.15},"name":"Nebraska","neighbors":[46,19,29,20,8,56],"property":{"prevRank":41,"prevValue":3.88,"rank":41,"value":4.31},"sales":{"prevRank":10,"prevValue":5.48,"rank":15,"value":5.15},"total":{"prevRank":28,"prevValue":5.01,"rank":28,"value":5.0},"unemployment":{"prevRank":11,"prevValue":5.55,"rank":11,"value":5.54}},{"abbr":"NV","corporate":{"prevRank":25,"prevValue":5.14,"rank":25,"value":5.13},"id":32,"individual":{"prevRank":5,"prevValue":8.43,"rank":5,"value":8.4},"name":"Nevada","neighbors":[16,49,4,6,41],"property":{"prevRank":10,"prevValue":5.95,"rank":5,"value":6.17},"sales":{"prevRank":44,"prevValue":3.89,"rank":44,"value":3.89},"total":{"prevRank":7,"prevValue":5.88,"rank":7,"value":5.9},"unemployment":{"prevRank":47,"prevValue":4.17,"rank":47,"value":4.28}},{"abbr":"NH","corporate":{"prevRank":43,"prevValue":4.38,"rank":41,"value":4.41},"id":33,"individual":{"prevRank":9,"prevValue":6.39,"rank":9,"value":6.37},"name":"New Hampshire","neighbors":[50,23,25],"property":{"prevRank":44,"prevValue":3.77,"rank":47,"value":3.7},"sales":{"prevRank":1,"prevValue":9.06,"rank":1,"value":9.08},"total":{"prevRank":6,"prevValue":6.01,"rank":6,"value":6.05},"unemployment":{"prevRank":45,"prevValue":4.44,"rank":44,"value":4.44}},{"abbr":"NJ","corporate":{"prevRank":49,"prevValue":3.56,"rank":48,"value":3.74},"id":34,"individual":{"prevRank":50,"prevValue":1.86,"rank":50,"value":1.86},"name":"New Jersey","neighbors":[10,42,36],"property":{"prevRank":47,"prevValue":3.37,"rank":46,"value":3.75},"sales":{"prevRank":42,"prevValue":3.98,"rank":42,"value":4.02},"total":{"prevRank":50,"prevValue":3.24,"rank":50,"value":3.34},"unemployment":{"prevRank":30,"prevValue":4.83,"rank":31,"value":4.84}},{"abbr":"NM","corporate":{"prevRank":20,"prevValue":5.4,"rank":9,"value":5.85},"id":35,"individual":{"prevRank":31,"prevValue":4.81,"rank":31,"value":4.8},"name":"New Mexico","neighbors":[4,49,8,40,48],"property":{"prevRank":1,"prevValue":6.73,"rank":1,"value":6.53},"sales":{"prevRank":41,"prevValue":4.02,"rank":41,"value":4.05},"total":{"prevRank":22,"prevValue":5.13,"rank":23,"value":5.17},"unemployment":{"prevRank":8,"prevValue":5.61,"rank":9,"value":5.6}},{"abbr":"NY","corporate":{"prevRank":13,"prevValue":5.58,"rank":15,"value":5.56},"id":36,"individual":{"prevRank":48,"prevValue":3.06,"rank":48,"value":3.05},"name":"New York","neighbors":[34,42,50,25,9],"property":{"prevRank":46,"prevValue":3.61,"rank":45,"value":3.77},"sales":{"prevRank":43,"prevValue":3.91,"rank":43,"value":3.96},"total":{"prevRank":49,"prevValue":4.01,"rank":48,"value":4.06},"unemployment":{"prevRank":38,"prevValue":4.68,"rank":38,"value":4.67}},{"abbr":"NC","corporate":{"prevRank":3,"prevValue":6.11,"rank":4,"value":6.09},"id":37,"individual":{"prevRank":16,"prevValue":5.73,"rank":16,"value":5.71},"name":"North Carolina","neighbors":[51,47,13,45],"property":{"prevRank":34,"prevValue":4.75,"rank":26,"value":5.17},"sales":{"prevRank":21,"prevValue":4.92,"rank":22,"value":4.96},"total":{"prevRank":15,"prevValue":5.43,"rank":10,"value":5.51},"unemployment":{"prevRank":10,"prevValue":5.56,"rank":10,"value":5.55}},{"abbr":"ND","corporate":{"prevRank":19,"prevValue":5.41,"rank":8,"value":5.86},"id":38,"individual":{"prevRank":20,"prevValue":5.24,"rank":20,"value":5.23},"name":"North Dakota","neighbors":[27,46,30],"property":{"prevRank":3,"prevValue":6.51,"rank":12,"value":5.65},"sales":{"prevRank":27,"prevValue":4.63,"rank":29,"value":4.61},"total":{"prevRank":16,"prevValue":5.36,"rank":17,"value":5.29},"unemployment":{"prevRank":13,"prevValue":5.46,"rank":12,"value":5.43}},{"abbr":"OH","corporate":{"prevRank":42,"prevValue":4.4,"rank":42,"value":4.39},"id":39,"individual":{"prevRank":44,"prevValue":3.86,"rank":43,"value":3.96},"name":"Ohio","neighbors":[42,54,21,18,26],"property":{"prevRank":9,"prevValue":6.13,"rank":6,"value":6.14},"sales":{"prevRank":32,"prevValue":4.49,"rank":34,"value":4.4},"total":{"prevRank":38,"prevValue":4.67,"rank":39,"value":4.64},"unemployment":{"prevRank":7,"prevValue":5.67,"rank":6,"value":5.65}},{"abbr":"OK","corporate":{"prevRank":8,"prevValue":5.8,"rank":11,"value":5.79},"id":40,"individual":{"prevRank":33,"prevValue":4.66,"rank":33,"value":4.64},"name":"Oklahoma","neighbors":[20,29,5,48,35,8],"property":{"prevRank":19,"prevValue":5.35,"rank":29,"value":5.11},"sales":{"prevRank":39,"prevValue":4.04,"rank":39,"value":4.08},"total":{"prevRank":27,"prevValue":5.01,"rank":30,"value":4.97},"unemployment":{"prevRank":1,"prevValue":6.35,"rank":1,"value":6.34}},{"abbr":"OR","corporate":{"prevRank":33,"prevValue":4.82,"rank":49,"value":3.19},"id":41,"individual":{"prevRank":38,"prevValue":4.43,"rank":38,"value":4.42},"name":"Oregon","neighbors":[6,32,16,53],"property":{"prevRank":18,"prevValue":5.36,"rank":16,"value":5.4},"sales":{"prevRank":4,"prevValue":8.82,"rank":4,"value":8.82},"total":{"prevRank":8,"prevValue":5.74,"rank":15,"value":5.42},"unemployment":{"prevRank":36,"prevValue":4.69,"rank":36,"value":4.74}},{"abbr":"PA","corporate":{"prevRank":46,"prevValue":4.19,"rank":43,"value":4.2},"id":42,"individual":{"prevRank":19,"prevValue":5.38,"rank":19,"value":5.41},"name":"Pennsylvania","neighbors":[36,34,10,24,54,39],"property":{"prevRank":21,"prevValue":5.24,"rank":15,"value":5.45},"sales":{"prevRank":17,"prevValue":5.05,"rank":17,"value":5.09},"total":{"prevRank":29,"prevValue":4.97,"rank":27,"value":5.01},"unemployment":{"prevRank":42,"prevValue":4.56,"rank":40,"value":4.55}},{"abbr":"RI","corporate":{"prevRank":40,"prevValue":4.57,"rank":39,"value":4.55},"id":44,"individual":{"prevRank":29,"prevValue":4.88,"rank":29,"value":4.86},"name":"Rhode Island","neighbors":[9,25],"property":{"prevRank":45,"prevValue":3.63,"rank":42,"value":4.19},"sales":{"prevRank":25,"prevValue":4.76,"rank":25,"value":4.78},"total":{"prevRank":39,"prevValue":4.57,"rank":37,"value":4.68},"unemployment":{"prevRank":31,"prevValue":4.81,"rank":30,"value":4.86}},{"abbr":"SC","corporate":{"prevRank":4,"prevValue":6.03,"rank":5,"value":6.02},"id":45,"individual":{"prevRank":34,"prevValue":4.63,"rank":34,"value":4.62},"name":"South Carolina","neighbors":[13,37],"property":{"prevRank":30,"prevValue":4.98,"rank":34,"value":4.6},"sales":{"prevRank":31,"prevValue":4.53,"rank":31,"value":4.55},"total":{"prevRank":30,"prevValue":4.96,"rank":33,"value":4.92},"unemployment":{"prevRank":26,"prevValue":4.88,"rank":24,"value":4.96}},{"abbr":"SD","corporate":{"prevRank":1,"prevValue":10.0,"rank":1,"value":10.0},"id":46,"individual":{"prevRank":1,"prevValue":10.0,"rank":1,"value":10.0},"name":"South Dakota","neighbors":[38,27,19,31,56,30],"property":{"prevRank":22,"prevValue":5.21,"rank":20,"value":5.26},"sales":{"prevRank":35,"prevValue":4.39,"rank":33,"value":4.42},"total":{"prevRank":2,"prevValue":7.34,"rank":2,"value":7.42},"unemployment":{"prevRank":44,"prevValue":4.52,"rank":42,"value":4.52}},{"abbr":"TN","corporate":{"prevRank":24,"prevValue":5.15,"rank":24,"value":5.13},"id":47,"individual":{"prevRank":8,"prevValue":7.09,"rank":8,"value":7.07},"name":"Tennessee","neighbors":[21,51,37,13,1,28,5,29],"property":{"prevRank":31,"prevValue":4.92,"rank":33,"value":4.68},"sales":{"prevRank":47,"prevValue":3.54,"rank":47,"value":3.53},"total":{"prevRank":18,"prevValue":5.29,"rank":18,"value":5.25},"unemployment":{"prevRank":24,"prevValue":4.96,"rank":26,"value":4.96}},{"abbr":"TX","corporate":{"prevRank":47,"prevValue":3.96,"rank":47,"value":3.95},"id":48,"individual":{"prevRank":6,"prevValue":7.9,"rank":6,"value":7.88},"name":"Texas","neighbors":[35,40,5,22],"property":{"prevRank":38,"prevValue":4.36,"rank":36,"value":4.54},"sales":{"prevRank":36,"prevValue":4.34,"rank":35,"value":4.38},"total":{"prevRank":13,"prevValue":5.46,"rank":11,"value":5.46},"unemployment":{"prevRank":12,"prevValue":5.51,"rank":16,"value":5.23}},{"abbr":"UT","corporate":{"prevRank":12,"prevValue":5.6,"rank":14,"value":5.59},"id":49,"individual":{"prevRank":10,"prevValue":6.1,"rank":10,"value":6.08},"name":"Utah","neighbors":[16,56,8,35,4,32],"property":{"prevRank":5,"prevValue":6.42,"rank":7,"value":5.98},"sales":{"prevRank":22,"prevValue":4.91,"rank":23,"value":4.92},"total":{"prevRank":9,"prevValue":5.7,"rank":8,"value":5.6},"unemployment":{"prevRank":15,"prevValue":5.36,"rank":17,"value":5.2}},{"abbr":"VT","corporate":{"prevRank":45,"prevValue":4.19,"rank":44,"value":4.18},"id":50,"individual":{"prevRank":39,"prevValue":4.37,"rank":39,"value":4.36},"name":"Vermont","neighbors":[36,33,25],"property":{"prevRank":49,"prevValue":2.84,"rank":49,"value":3.3},"sales":{"prevRank":16,"prevValue":5.11,"rank":16,"value":5.14},"total":{"prevRank":44,"prevValue":4.35,"rank":43,"value":4.45},"unemployment":{"prevRank":16,"prevValue":5.32,"rank":15,"value":5.31}},{"abbr":"VA","corporate":{"prevRank":14,"prevValue":5.54,"rank":16,"value":5.53},"id":51,"individual":{"prevRank":35,"prevValue":4.62,"rank":35,"value":4.6},"name":"Virginia","neighbors":[37,47,21,54,24,11],"property":{"prevRank":32,"prevValue":4.84,"rank":27,"value":5.16},"sales":{"prevRank":11,"prevValue":5.4,"rank":11,"value":5.36},"total":{"prevRank":25,"prevValue":5.02,"rank":26,"value":5.04},"unemployment":{"prevRank":41,"prevValue":4.56,"rank":46,"value":4.39}},{"abbr":"WA","corporate":{"prevRank":41,"prevValue":4.45,"rank":40,"value":4.43},"id":53,"individual":{"prevRank":6,"prevValue":7.9,"rank":6,"value":7.88},"name":"Washington","neighbors":[16,41],"property":{"prevRank":27,"prevValue":5.02,"rank":18,"value":5.39},"sales":{"prevRank":49,"prevValue":2.91,"rank":48,"value":2.95},"total":{"prevRank":19,"prevValue":5.28,"rank":16,"value":5.33},"unemployment":{"prevRank":19,"prevValue":5.12,"rank":19,"value":5.11}},{"abbr":"WV","corporate":{"prevRank":15,"prevValue":5.47,"rank":17,"value":5.46},"id":54,"individual":{"prevRank":28,"prevValue":4.9,"rank":28,"value":4.88},"name":"West Virginia","neighbors":[39,42,24,51,21],"property":{"prevRank":17,"prevValue":5.37,"rank":10,"value":5.73},"sales":{"prevRank":18,"prevValue":5.04,"rank":19,"value":5.03},"total":{"prevRank":23,"prevValue":5.12,"rank":22,"value":5.17},"unemployment":{"prevRank":29,"prevValue":4.86,"rank":28,"value":4.94}},{"abbr":"WI","corporate":{"prevRank":30,"prevValue":4.9,"rank":30,"value":4.89},"id":55,"individual":{"prevRank":37,"prevValue":4.51,"rank":37,"value":4.5},"name":"Wisconsin","neighbors":[26,27,19,17],"property":{"prevRank":23,"prevValue":5.14,"rank":17,"value":5.4},"sales":{"prevRank":7,"prevValue":5.78,"rank":7,"value":5.82},"total":{"prevRank":26,"prevValue":5.01,"rank":25,"value":5.06},"unemployment":{"prevRank":37,"prevValue":4.68,"rank":35,"value":4.76}},{"abbr":"WY","corporate":{"prevRank":1,"prevValue":10.0,"rank":1,"value":10.0},"id":56,"individual":{"prevRank":1,"prevValue":10.0,"rank":1,"value":10.0},"name":"Wyoming","neighbors":[30,46,31,8,49,16],"property":{"prevRank":39,"prevValue":4.31,"rank":39,"value":4.34},"sales":{"prevRank":6,"prevValue":6.04,"rank":6,"value":6.06},"total":{"prevRank":1,"prevValue":7.62,"rank":1,"value":7.72},"unemployment":{"prevRank":27,"prevValue":4.87,"rank":29,"value":4.9}},{"abbr":"DC","corporate":{"prevRank":15,"prevValue":5.52,"rank":17,"value":5.51},"id":11,"individual":{"prevRank":45,"prevValue":3.68,"rank":45,"value":3.67},"name":"District of Columbia","neighbors":[24,51],"property":{"prevRank":49,"prevValue":3.28,"rank":49,"value":3.57},"sales":{"prevRank":36,"prevValue":4.38,"rank":34,"value":4.41},"total":{"prevRank":47,"prevValue":4.24,"rank":46,"value":4.32},"unemployment":{"prevRank":35,"prevValue":4.74,"rank":37,"value":4.73}}]